linkage/__init__.py
vc_config/__init__.py
vc_config/default.json
vc_utils-0.0.9.dist-info/METADATA
vc_utils-0.0.9.dist-info/WHEEL
vc_utils-0.0.9.dist-info/top_level.txt
vc_utils-0.0.9.dist-info/RECORD
