Metadata-Version: 2.4
Name: vc-utils
Version: 0.0.9
Summary: Vulcan Coalition utililities
Home-page: https://github.com/vulcan-coalition/vulcan-utils
Author: Chatavut Viriyasuthee
Author-email: chatavut@lab.ai
Classifier: Programming Language :: Python :: 3
Classifier: License :: OSI Approved :: Apache Software License
Classifier: Operating System :: OS Independent
Requires-Python: >=3.9
Requires-Dist: shortuuid
Requires-Dist: dotenv
Requires-Dist: requests
Dynamic: author
Dynamic: author-email
Dynamic: classifier
Dynamic: description
Dynamic: description-content-type
Dynamic: home-page
Dynamic: requires-dist
Dynamic: requires-python
Dynamic: summary
